py4xs/__init__.py
py4xs/data2d.py
py4xs/detector_config.py
py4xs/exp_para.py
py4xs/hdf.py
py4xs/local.py
py4xs/mask.py
py4xs/plot.py
py4xs/slnxs.py
py4xs/utils.py
py4xs-2023.1.23.0.dist-info/LICENSE.txt
py4xs-2023.1.23.0.dist-info/METADATA
py4xs-2023.1.23.0.dist-info/WHEEL
py4xs-2023.1.23.0.dist-info/top_level.txt
py4xs-2023.1.23.0.dist-info/RECORD
