Metadata-Version: 2.1
Name: py4xs
Version: 2023.1.23.0
Summary: python package for processing x-ray scattering data
Home-page: 
Author: Lin Yang
Author-email: lyang@bnl.gov
License: BSD
Keywords: x-ray scattering
Classifier: Intended Audience :: Science/Research
Classifier: Topic :: Scientific/Engineering :: Information Analysis
Classifier: Development Status :: 3 - Alpha
Classifier: Programming Language :: Python :: 3.6
Requires-Python: >=3
License-File: LICENSE.txt
Requires-Dist: fabio
Requires-Dist: h5py
Requires-Dist: pillow
Requires-Dist: matplotlib
Requires-Dist: numpy
Requires-Dist: scipy (>-=1.6)
